{
 "race": "2012 Turkey Recovery 5k",
 "results": [
  {
   "name": "Will McNabb",
   "category": "Male 15-11",
   "time": "00:22:47"
  },
  {
   "name": "Natalie Krause",
   "category": "Female 30-39",
   "time": "00:23:49"
  },
  {
   "name": "Travis Bladecki",
   "category": "Male 20-29",
   "time": "00:24:10"
  },
  {
   "name": "Craig Miller",
   "category": "Male 50-59",
   "time": "00:25:02"
  },
  {
   "name": "Mark Kingery",
   "category": "Male 40-49",
   "time": "00:25:35"
  },
  {
   "name": "Scott Bush",
   "category": "Male 30-39",
   "time": "00:25:59"
  },
  {
   "name": "Michael Macritchie",
   "category": "Male 30-39",
   "time": "00:26:21"
  },
  {
   "name": "Jason Pritchard",
   "category": "Male 30-39",
   "time": "00:26:51"
  },
  {
   "name": "Bittany Siroki",
   "category": "Female 20-29",
   "time": "00:27:13"
  },
  {
   "name": "Stephanie Sandard",
   "category": "Female 20-29",
   "time": "00:27:27"
  },
  {
   "name": "Tim Kennedy",
   "category": "Male 50-59",
   "time": "00:27:43"
  },
  {
   "name": "Paul Schweitzer",
   "category": "Male 50-59",
   "time": "00:27:55"
  },
  {
   "name": "Bill Dickinson",
   "category": "Male 30-39",
   "time": "00:28:03"
  },
  {
   "name": "Jeromie Pritchard",
   "category": "Male 30-39",
   "time": "00:28:44"
  },
  {
   "name": "Tanja Pritchard",
   "category": "Female 20-29",
   "time": "00:29:01"
  },
  {
   "name": "Jessica Pritchard",
   "category": "Female 20-29",
   "time": "00:29:01"
  },
  {
   "name": "Lauren Kawecki",
   "category": "Female 20-29",
   "time": "00:29:58"
  },
  {
   "name": "Russ Roberson",
   "category": "Male 40-49",
   "time": "00:30:27"
  },
  {
   "name": "Conor McDonald",
   "category": "Male 10 Unde",
   "time": "00:30:39"
  },
  {
   "name": "Marc McDonald",
   "category": "Male 30-39",
   "time": "00:30:42"
  },
  {
   "name": "Megan McDonald",
   "category": "Female 30-39",
   "time": "00:30:46"
  },
  {
   "name": "Alex Vaughn",
   "category": "Male 15-11",
   "time": "00:31:28"
  },
  {
   "name": "Ken Vaughn",
   "category": "Male 30-39",
   "time": "00:31:29"
  },
  {
   "name": "Kelly Smith",
   "category": "Female 50-59",
   "time": "00:31:32"
  },
  {
   "name": "Nikki Melendez",
   "category": "Female 30-39",
   "time": "00:31:36"
  },
  {
   "name": "Amanda Hall",
   "category": "Female 30-39",
   "time": "00:31:51"
  },
  {
   "name": "Tom Hutmacher",
   "category": "Male 60-69",
   "time": "00:32:47"
  },
  {
   "name": "Tanya Barna",
   "category": "Female 30-39",
   "time": "00:33:31"
  },
  {
   "name": "Mike Steinhubel",
   "category": "Male 40-49",
   "time": "00:33:46"
  },
  {
   "name": "Olga Felton",
   "category": "Female 50-59",
   "time": "00:33:58"
  },
  {
   "name": "Lydia Sandoval",
   "category": "Female 50-59",
   "time": "00:34:03"
  },
  {
   "name": "Nicole Roberson",
   "category": "Female 30-39",
   "time": "00:34:10"
  },
  {
   "name": "Keith Losey",
   "category": "Male 50-59",
   "time": "00:34:41"
  },
  {
   "name": "Karen Vinson",
   "category": "Female 40-49",
   "time": "00:34:44"
  },
  {
   "name": "Lorie Arnold",
   "category": "Female 40-49",
   "time": "00:34:45"
  },
  {
   "name": "Jim Kaminski",
   "category": "Male 70+",
   "time": "00:35:00"
  },
  {
   "name": "Tina Sopher",
   "category": "Female 40-49",
   "time": "00:36:46"
  },
  {
   "name": "Matt Taylor",
   "category": "Male 40-49",
   "time": "00:36:47"
  },
  {
   "name": "Caris Daily",
   "category": "Female 20-29",
   "time": "00:41:14"
  },
  {
   "name": "Brenda Daily",
   "category": "Female 40-49",
   "time": "00:41:17"
  },
  {
   "name": "Tiffany Daray",
   "category": "Female 30-39",
   "time": "00:41:37"
  },
  {
   "name": "Michael Daray",
   "category": "Male 30-39",
   "time": "00:41:38"
  }
 ]
}